wakaranai/__init__.py
wakaranai/__main__.py
wakaranai/quiz.py
wakaranai/romaji.py
wakaranai-0.0.1.dist-info/METADATA
wakaranai-0.0.1.dist-info/WHEEL
wakaranai-0.0.1.dist-info/licenses/LICENSE
wakaranai-0.0.1.dist-info/RECORD
