Metadata-Version: 2.1
Name: wakaranai
Version: 0.0.1
Summary: An educational tool for learning hiragana and katakana
Project-URL: Source Code, https://github.com/guidanoli/wakaranai
Project-URL: Bug Tracker, https://github.com/guidanoli/wakaranai/issues
Author: Guilherme Dantas
License-File: LICENSE
Keywords: education,hiragana,japanese,katakana,learning
Classifier: Environment :: Console
Classifier: Intended Audience :: Education
Classifier: License :: OSI Approved :: GNU General Public License v3 (GPLv3)
Classifier: Natural Language :: English
Classifier: Natural Language :: Japanese
Classifier: Operating System :: OS Independent
Classifier: Programming Language :: Python :: 3
Classifier: Topic :: Education
Requires-Python: >=3.8
Requires-Dist: colorama==0.4.6
